testrail_api/__init__.py
testrail_api/__version__.py
testrail_api/_category.py
testrail_api/_enums.py
testrail_api/_exception.py
testrail_api/_session.py
testrail_api/_testrail_api.py
testrail_api-1.13.5.dist-info/licenses/LICENSE
testrail_api-1.13.5.dist-info/METADATA
testrail_api-1.13.5.dist-info/WHEEL
testrail_api-1.13.5.dist-info/top_level.txt
testrail_api-1.13.5.dist-info/RECORD
